mcp_server_rss/__init__.py
mcp_server_rss/__main__.py
mcp_server_rss/feed_detect.py
mcp_server_rss/server.py
mcp_server_rss-0.1.0.dist-info/METADATA
mcp_server_rss-0.1.0.dist-info/WHEEL
mcp_server_rss-0.1.0.dist-info/entry_points.txt
mcp_server_rss-0.1.0.dist-info/RECORD
