Metadata-Version: 2.4
Name: mcp-server-rss
Version: 0.1.0
Summary: RSS feed parser server for Model Context Protocol (MCP)
Author-email: yareyaredesuyo <yareyaredesuyo@gmail.com>
License-Expression: MIT
Keywords: feed,llm,mcp,model-context-protocol,parser,rss
Classifier: Development Status :: 4 - Beta
Classifier: Intended Audience :: Developers
Classifier: License :: OSI Approved :: MIT License
Classifier: Programming Language :: Python :: 3
Classifier: Programming Language :: Python :: 3.10
Classifier: Topic :: Internet :: WWW/HTTP :: Indexing/Search
Classifier: Topic :: Software Development :: Libraries :: Python Modules
Requires-Python: >=3.10
Requires-Dist: beautifulsoup4>=4.12.0
Requires-Dist: fastmcp>=2.5.2
Requires-Dist: feedparser>=6.0.0
Requires-Dist: httpx>=0.24.0
Requires-Dist: pydantic>=2.0.0
